README.rst
setup.py
superwrap.egg-info/PKG-INFO
superwrap.egg-info/SOURCES.txt
superwrap.egg-info/dependency_links.txt
superwrap.egg-info/entry_points.txt
superwrap.egg-info/namespace_packages.txt
superwrap.egg-info/top_level.txt
virtualenvwrapper/__init__.py
virtualenvwrapper/the_scripts.py