Metadata-Version: 1.1
Name: superwrap
Version: 0.0.2
Summary: The easy way to contribute to python packages
Home-page: https://github.com/spulec/superwrap
Author: Steve Pulec
Author-email: spulec@gmail.com
License: Apache License 2.0
Platform: UNKNOWN
Requires: virtualenv
Requires: virtualenvwrapper (>=2.9)
Requires: requests (>=0.12.1)
